{"settings":{"appVersion":1,"siteName":"templateContact001","backgroundColor":"white","googleFonts":["Dancing Script"],"scripts":[]},"elementsRoot":{"typeName":"body","description":"Body","styleName":"","childsAllowed":"all","tag":"body","style":[],"phone":[],"attributes":[],"childs":[{"typeName":"divAutocenter","description":"Autocentered div","childsAllowed":"all","tag":"div","style":[["padding","0 16px",true]],"phone":[],"attributes":[],"childs":[{"typeName":"divFlex","description":"Flex","childsAllowed":"divFlexChild","tag":"div","style":[],"phone":[["flex-direction","column",true]],"attributes":[],"childs":[{"typeName":"divFlexChild","description":"Flex child","childsAllowed":"all","tag":"div","style":[["flex-direction","column",true],["flex-grow","1",true],["padding","0 32px 0 0",true]],"phone":[["padding","0 0 32px 0",true]],"attributes":[],"childs":[{"typeName":"titleh1","description":"H1","childsAllowed":"none","tag":"h1","style":[["font-size","2em",true],["font-weight","800",true],["height","max-content",true],["padding","0 0 16px 0",true],["width","100%",true]],"phone":[],"attributes":[],"childs":[],"text":"Contact us"},{"typeName":"text","description":"Text","childsAllowed":"none","tag":"div","style":[["font-size","1em",true],["height","max-content",true],["padding","0 0 16px 0",true],["width","100%",true]],"phone":[],"attributes":[],"childs":[],"text":"We are here to answer any questions you may have about our services. Reach out to  us and we'll respond as soon as we can."},{"typeName":"formInputText","description":"Input text with pattern validation","childsAllowed":"none","tag":"div","style":[],"phone":[],"attributes":[["class","formInputText"]],"childs":[{"typeName":"formInputTextField","description":"Input text","childsAllowed":"none","tag":"input","style":[],"phone":[],"attributes":[["id","formName"],["type","text"],["placeholder","yes"],["pattern","[^0-9]*"],["autocomplete","off"]],"childs":[],"text":""},{"typeName":"formInputTextLabel","description":"Label","childsAllowed":"none","tag":"label","style":[],"phone":[],"attributes":[],"childs":[],"text":"Name"},{"typeName":"formInputTextSpan","description":"Error message","childsAllowed":"none","tag":"span","style":[],"phone":[],"attributes":[],"childs":[],"text":"Numbers are not allowed"}],"text":""},{"typeName":"formInputText","description":"Input text with pattern validation","childsAllowed":"none","tag":"div","style":[],"phone":[],"attributes":[["class","formInputText"]],"childs":[{"typeName":"formInputTextField","description":"Input text","childsAllowed":"none","tag":"input","style":[],"phone":[],"attributes":[["id","formMail"],["type","text"],["placeholder","yes"],["pattern","[a-z0-9._%+-]+@[a-z0-9.-]+\\.[a-z]{2,}$"],["autocomplete","off"]],"childs":[],"text":""},{"typeName":"formInputTextLabel","description":"Label","childsAllowed":"none","tag":"label","style":[],"phone":[],"attributes":[],"childs":[],"text":"Mail"},{"typeName":"formInputTextSpan","description":"Error message","childsAllowed":"none","tag":"span","style":[],"phone":[],"attributes":[],"childs":[],"text":"This is not an email"}],"text":""},{"typeName":"formInputTextarea","description":"Input textarea","childsAllowed":"none","tag":"div","style":[],"phone":[],"attributes":[["class","formInputTextarea"]],"childs":[{"typeName":"formInputTextareaField","description":"Input textarea","childsAllowed":"none","tag":"textarea","style":[],"phone":[],"attributes":[["id","formDescription"],["placeholder","yes"]],"childs":[],"text":""},{"typeName":"formInputTextareaLabel","description":"Label","childsAllowed":"none","tag":"label","style":[],"phone":[],"attributes":[],"childs":[],"text":"Description"}],"text":""},{"typeName":"divFlex","description":"Flex","childsAllowed":"divFlexChild","tag":"div","style":[["justify-content","center",true]],"phone":[],"attributes":[],"childs":[{"typeName":"divFlexChild","description":"Flex child","childsAllowed":"all","tag":"div","style":[["padding","16px 0 0 0",true]],"phone":[],"attributes":[],"childs":[{"typeName":"formButton","description":"Button for forms","childsAllowed":"none","tag":"button","style":[],"phone":[],"attributes":[["class","formButton"]],"childs":[],"text":"Send"}],"text":""}],"text":""}],"text":""},{"typeName":"divFlexChild","description":"Flex child","childsAllowed":"all","tag":"div","style":[["min-width","25%",true],["max-width","25%",true]],"phone":[["min-width","100%",true],["max-width","100%",true]],"attributes":[],"childs":[{"typeName":"div","description":"Div","childsAllowed":"all","tag":"div","style":[["border","dashed 1px grey",true],["border-radius","15px",true],["height","max-content",true],["padding","16px",true],["width","100%",true]],"phone":[],"attributes":[],"childs":[{"typeName":"titleh2","description":"H2","childsAllowed":"none","tag":"h2","style":[["font-size","1.5em",true],["font-weight","300",true],["height","max-content",true],["padding","0",true],["width","100%",true]],"phone":[],"attributes":[],"childs":[],"text":"Phone"},{"typeName":"linkBox","description":"Link box","childsAllowed":"all","tag":"a","style":[["height","max-content",true],["text-decoration","none",true],["width","100%",true]],"phone":[["height","max-content",true],["width","max-content",true]],"attributes":[["href","tel:+0123456"],["target","_blank"]],"childs":[{"typeName":"text","description":"Text","childsAllowed":"none","tag":"div","style":[["color","rgb(0, 150, 255)",true],["font-size","1em",true],["height","max-content",true],["text-align","right",true],["width","100%",true]],"phone":[],"attributes":[],"childs":[],"text":"+0123456"}],"text":""},{"typeName":"titleh2","description":"H2","childsAllowed":"none","tag":"h2","style":[["font-size","1.5em",true],["font-weight","300",true],["height","max-content",true],["padding","0",true],["width","100%",true]],"phone":[],"attributes":[],"childs":[],"text":"Mail"},{"typeName":"linkBox","description":"Link box","childsAllowed":"all","tag":"a","style":[["height","max-content",true],["text-decoration","none",true],["width","100%",true]],"phone":[["height","max-content",true],["width","max-content",true]],"attributes":[["href","mailto:mail@domain.com"],["target","_blank"]],"childs":[{"typeName":"text","description":"Text","childsAllowed":"none","tag":"div","style":[["color","rgb(0, 150, 255)",true],["font-size","1em",true],["height","max-content",true],["text-align","right",true],["width","100%",true]],"phone":[],"attributes":[],"childs":[],"text":"mail@domain.com"}],"text":""},{"typeName":"titleh2","description":"H2","childsAllowed":"none","tag":"h2","style":[["font-size","1.5em",true],["font-weight","300",true],["height","max-content",true],["padding","0",true],["width","100%",true]],"phone":[],"attributes":[],"childs":[],"text":"Address"},{"typeName":"text","description":"Text","childsAllowed":"none","tag":"div","style":[["font-size","1em",true],["height","max-content",true],["text-align","right",true],["width","100%",true]],"phone":[],"attributes":[],"childs":[],"text":"Pç Catalunya 1"},{"typeName":"text","description":"Text","childsAllowed":"none","tag":"div","style":[["font-size","1em",true],["height","max-content",true],["text-align","right",true],["width","100%",true]],"phone":[],"attributes":[],"childs":[],"text":"08002 Barcelona"},{"typeName":"titleh2","description":"H2","childsAllowed":"none","tag":"h2","style":[["font-size","1.5em",true],["font-weight","300",true],["height","max-content",true],["padding","0",true],["width","100%",true]],"phone":[],"attributes":[],"childs":[],"text":"Follow us at"},{"typeName":"divFlex","description":"Flex","childsAllowed":"divFlexChild","tag":"div","style":[["justify-content","flex-end",true]],"phone":[],"attributes":[],"childs":[{"typeName":"divFlexChild","description":"Flex child","childsAllowed":"all","tag":"div","style":[],"phone":[],"attributes":[],"childs":[{"typeName":"div","description":"Div","childsAllowed":"all","tag":"div","style":[["height","max-content",true],["padding","4px",true]],"phone":[],"attributes":[],"childs":[{"typeName":"linkBox","description":"Link box","childsAllowed":"all","tag":"a","style":[["height","max-content",true],["text-decoration","none",true],["width","max-content",true]],"phone":[["height","max-content",true],["width","max-content",true]],"attributes":[["href","/"],["target","_blank"]],"childs":[{"typeName":"image","description":"Image","childsAllowed":"none","tag":"img","style":[],"phone":[],"attributes":[["src","/tool/images/logo-linkedin.svg"],["width","24px"],["height","24px"]],"childs":[],"text":""}],"text":""}],"text":""}],"text":""},{"typeName":"divFlexChild","description":"Flex child","childsAllowed":"all","tag":"div","style":[],"phone":[],"attributes":[],"childs":[{"typeName":"div","description":"Div","childsAllowed":"all","tag":"div","style":[["height","max-content",true],["padding","4px",true]],"phone":[],"attributes":[],"childs":[{"typeName":"linkBox","description":"Link box","childsAllowed":"all","tag":"a","style":[["height","max-content",true],["text-decoration","none",true],["width","max-content",true]],"phone":[["height","max-content",true],["width","max-content",true]],"attributes":[["href","/"],["target","_blank"]],"childs":[{"typeName":"image","description":"Image","childsAllowed":"none","tag":"img","style":[],"phone":[],"attributes":[["src","/tool/images/logo-facebook.svg"],["width","24px"],["height","24px"]],"childs":[],"text":""}],"text":""}],"text":""}],"text":""},{"typeName":"divFlexChild","description":"Flex child","childsAllowed":"all","tag":"div","style":[],"phone":[],"attributes":[],"childs":[{"typeName":"div","description":"Div","childsAllowed":"all","tag":"div","style":[["height","max-content",true],["padding","4px",true]],"phone":[],"attributes":[],"childs":[{"typeName":"linkBox","description":"Link box","childsAllowed":"all","tag":"a","style":[["height","max-content",true],["text-decoration","none",true],["width","max-content",true]],"phone":[["height","max-content",true],["width","max-content",true]],"attributes":[["href","/"],["target","_blank"]],"childs":[{"typeName":"image","description":"Image","childsAllowed":"none","tag":"img","style":[],"phone":[],"attributes":[["src","/tool/images/logo-instagram.svg"],["width","24px"],["height","24px"]],"childs":[],"text":""}],"text":""}],"text":""}],"text":""}],"text":""}],"text":""}],"text":""}],"text":""}],"text":""}],"text":""}}